[{"newstitle":"ব্রিটেনের গুরুত্বপূর্ণ সামরিক কেন্দ্র হয়ে উঠছে ওমান","content":"ব্রিটেনের গুরুত্বপূর্ণ সামরিক কেন্দ্র হয়ে উঠছে ওমান ওমানে ব্রিটিশ সেনাবাহিনীর উপস্থিতি দিনের পর দিন বেড়েই চলেছে। ফলে দেশটি ব্রিটেনের জন্য কৌশলগতভাবে গুরুত্বপূর্ণ বৈশ্বিক কেন্দ্র হয়ে উঠছে। দুকম বন্দরের কাছে অবস্থিত রাস মাদরাকা জয়েন্ট ট্রেনিং এরিয়া বার বার ব্যবহার করছে সেনাবাহিনী। পরবর্তীতে বছরে প্রায় ছয় সপ্তাহ থেকে আট মাসেরও বেশি সময় এটি ব্যবহার করা হবে। বুধবার আর্মি টেকনোলজির এক প্রতিবেদনে এই তথ্য জানান হয়েছে। ২০২১ সালে ব্রিটিশ সরকারের সমন্বিত পর্যালোচনার সাথে সামঞ্জস্যপূর্ণ এই পদক্ষেপের উদ্দেশ্য হলো সামরিক মহড়া এবং প্রতিরক্ষা সম্পদ স্থাপনের মাধ্যমে আন্তর্জাতিক বিশ্বে ব্রিটেনের উপস্থিতি বাড়ানো। গত ১ নভেম্বর প্রতিরক্ষা সচিব বেন ওয়ালেস নিশ্চিত করেছেন যে সাইটটি বার্ষিক দুটি আলাদা প্রশিক্ষণ ব্লকের আয়োজন করবে। প্রতিটি প্রশিক্ষণ চার মাস পর্যন্ত স্থায়ী হবে। সূত্র : মিডল ইস্ট মনিটর","sourceurl":"https://www.dailynayadiganta.com/uk/708491/ব্রিটেনের-গুরুত্বপূর্ণ-সামরিক-কেন্দ্র-হয়ে-উঠছে-ওমান","sourcetitle":"www.dailynayadiganta.com","publishtime":"2022-11-24 23-26","mediaurl":"https://www.dailynayadiganta.com/resources/img/article/202211/708491_116.JPG","mediatype":0,"newstype":0,"category":0,"country":"bd","openwith":0,"top":0,"addedby":"test"}]